{
  "version": "1",
  "cognitoConfig": {
    "identityPoolName": "mmawebappaa31305d_identitypool_aa31305d",
    "allowUnauthenticatedIdentities": true,
    "resourceNameTruncated": "mmawebaa31305d",
    "userPoolName": "mmawebappaa31305d_userpool_aa31305d",
    "autoVerifiedAttributes": [
      "email"
    ],
    "mfaConfiguration": "OFF",
    "mfaTypes": [
      "SMS Text Message"
    ],
    "smsAuthenticationMessage": "Your authentication code is {####}",
    "smsVerificationMessage": "Your verification code is {####}",
    "emailVerificationSubject": "MMA Verification Code",
    "emailVerificationMessage": "<p>Please see below verification code.</p><h1>{####}</h1><p>Thank you!</p><p>Regards,<br/><b>MMA Team</b></p>",
    "defaultPasswordPolicy": false,
    "passwordPolicyMinLength": 8,
    "passwordPolicyCharacters": [
      "Requires Lowercase",
      "Requires Numbers",
      "Requires Symbols",
      "Requires Uppercase"
    ],
    "requiredAttributes": [
      "email"
    ],
    "aliasAttributes": [],
    "userpoolClientGenerateSecret": false,
    "userpoolClientRefreshTokenValidity": 30,
    "userpoolClientWriteAttributes": [],
    "userpoolClientReadAttributes": [],
    "userpoolClientLambdaRole": "mmawebaa31305d_userpoolclient_lambda_role",
    "userpoolClientSetAttributes": false,
    "sharedId": "aa31305d",
    "resourceName": "mmawebappaa31305d",
    "authSelections": "identityPoolAndUserPool",
    "useDefault": "manual",
    "usernameAttributes": [
      "email, phone_number"
    ],
    "userPoolGroupList": [],
    "serviceName": "Cognito",
    "useEnabledMfas": false,
    "authRoleArn": {
      "Fn::GetAtt": [
        "AuthRole",
        "Arn"
      ]
    },
    "unauthRoleArn": {
      "Fn::GetAtt": [
        "UnauthRole",
        "Arn"
      ]
    },
    "breakCircularDependency": false,
    "dependsOn": [],
    "userPoolGroups": false,
    "adminQueries": false,
    "thirdPartyAuth": false,
    "authProviders": [],
    "hostedUI": false
  }
}